aionut/__init__.py
aionut/client.py
aionut/exceptions.py
aionut/py.typed
aionut-4.3.3.dist-info/LICENSE
aionut-4.3.3.dist-info/METADATA
aionut-4.3.3.dist-info/WHEEL
aionut-4.3.3.dist-info/RECORD
