Metadata-Version: 2.1
Name: aionut
Version: 4.3.3
Summary: Asyncio Network UPS Tools
Home-page: https://github.com/bdraco/aionut
Author: J. Nick Koston
Author-email: nick@koston.org
Requires-Python: >=3.11,<4.0
Classifier: Development Status :: 2 - Pre-Alpha
Classifier: Intended Audience :: Developers
Classifier: License :: OSI Approved :: Apache Software License
Classifier: Natural Language :: English
Classifier: Operating System :: OS Independent
Classifier: Programming Language :: Python :: 3
Classifier: Programming Language :: Python :: 3.11
Classifier: Programming Language :: Python :: 3.12
Classifier: Topic :: Software Development :: Libraries
Project-URL: Bug Tracker, https://github.com/bdraco/aionut/issues
Project-URL: Changelog, https://github.com/bdraco/aionut/blob/main/CHANGELOG.md
Project-URL: Documentation, https://aionut.readthedocs.io
Project-URL: Repository, https://github.com/bdraco/aionut
